alibabacloud_workorder20210610/__init__.py
alibabacloud_workorder20210610/client.py
alibabacloud_workorder20210610/models/__init__.py
alibabacloud_workorder20210610/models/_close_ticket_request.py
alibabacloud_workorder20210610/models/_close_ticket_response.py
alibabacloud_workorder20210610/models/_close_ticket_response_body.py
alibabacloud_workorder20210610/models/_create_ticket_request.py
alibabacloud_workorder20210610/models/_create_ticket_response.py
alibabacloud_workorder20210610/models/_create_ticket_response_body.py
alibabacloud_workorder20210610/models/_create_ticket_shrink_request.py
alibabacloud_workorder20210610/models/_evaluate_ticket_request.py
alibabacloud_workorder20210610/models/_evaluate_ticket_response.py
alibabacloud_workorder20210610/models/_evaluate_ticket_response_body.py
alibabacloud_workorder20210610/models/_get_attachment_upload_url_request.py
alibabacloud_workorder20210610/models/_get_attachment_upload_url_response.py
alibabacloud_workorder20210610/models/_get_attachment_upload_url_response_body.py
alibabacloud_workorder20210610/models/_get_mq_consumer_tag_response.py
alibabacloud_workorder20210610/models/_get_mq_consumer_tag_response_body.py
alibabacloud_workorder20210610/models/_get_ticket_request.py
alibabacloud_workorder20210610/models/_get_ticket_response.py
alibabacloud_workorder20210610/models/_get_ticket_response_body.py
alibabacloud_workorder20210610/models/_list_categories_request.py
alibabacloud_workorder20210610/models/_list_categories_response.py
alibabacloud_workorder20210610/models/_list_categories_response_body.py
alibabacloud_workorder20210610/models/_list_products_request.py
alibabacloud_workorder20210610/models/_list_products_response.py
alibabacloud_workorder20210610/models/_list_products_response_body.py
alibabacloud_workorder20210610/models/_list_ticket_notes_request.py
alibabacloud_workorder20210610/models/_list_ticket_notes_response.py
alibabacloud_workorder20210610/models/_list_ticket_notes_response_body.py
alibabacloud_workorder20210610-1.0.1.dist-info/LICENSE
alibabacloud_workorder20210610-1.0.1.dist-info/METADATA
alibabacloud_workorder20210610-1.0.1.dist-info/WHEEL
alibabacloud_workorder20210610-1.0.1.dist-info/top_level.txt
alibabacloud_workorder20210610-1.0.1.dist-info/RECORD
